bits/__init__.py
bits/__main__.py
bits/base58.py
bits/blockchain.py
bits/config.py
bits/ecmath.py
bits/integrations.py
bits/keys.py
bits/p2p.py
bits/pem.py
bits/rpc.py
bits/tx.py
bits/utils.py
bits/bips/bip143.py
bits/bips/bip173.py
bits/bips/bip32.py
bits/bips/bip43.py
bits/bips/bip44.py
bits/bips/slip44.py
bits/bips/bip39/__init__.py
bits/bips/bip39/english.txt
bits/script/__init__.py
bits/script/constants.py
bits/script/utils.py
bits/wallet/__init__.py
bits/wallet/hd.py
bits-0.2.0.dist-info/LICENSE.txt
bits-0.2.0.dist-info/METADATA
bits-0.2.0.dist-info/WHEEL
bits-0.2.0.dist-info/entry_points.txt
bits-0.2.0.dist-info/top_level.txt
bits-0.2.0.dist-info/RECORD
