Metadata-Version: 2.1
Name: bits
Version: 0.2.0
Summary: bits is a cli tool and pure Python library for Bitcoin
Author-email: Jason Traub <jtraub91@gmail.com>
Project-URL: Source, https://github.com/jtraub91/bits
Classifier: Programming Language :: Python :: 3 :: Only
Classifier: Programming Language :: Python :: 3.7
Classifier: Programming Language :: Python :: 3.8
Classifier: Programming Language :: Python :: 3.9
Classifier: Programming Language :: Python :: 3.10
Classifier: Programming Language :: Python :: 3.11
Classifier: License :: OSI Approved :: MIT License
Classifier: Operating System :: OS Independent
Requires-Python: >=3.7
License-File: LICENSE.txt
Provides-Extra: dev
Requires-Dist: black; extra == "dev"
Requires-Dist: build; extra == "dev"
Requires-Dist: ipdb; extra == "dev"
Requires-Dist: pip-chill; extra == "dev"
Requires-Dist: pre-commit; extra == "dev"
Requires-Dist: pylint; extra == "dev"
Requires-Dist: pytest-cov; extra == "dev"
Requires-Dist: reorder-python-imports; extra == "dev"
Requires-Dist: twine; extra == "dev"
